AutoDiff/__init__.py
AutoDiff/api.py
AutoDiff/nn.py
AutoDiff/root_finder.py
AutoDiff/tests/__init__.py
AutoDiff/tests/test_AutoDiff.py
AutoDiff/tests/test_root_finder.py
AutoDiff_207_15-0.1.data/data/LICENSE
AutoDiff_207_15-0.1.dist-info/LICENSE
AutoDiff_207_15-0.1.dist-info/METADATA
AutoDiff_207_15-0.1.dist-info/WHEEL
AutoDiff_207_15-0.1.dist-info/top_level.txt
AutoDiff_207_15-0.1.dist-info/RECORD
