Metadata-Version: 2.1
Name: AutoDiff-207-15
Version: 0.1
Summary: Autodifferentiation package
Home-page: UNKNOWN
Author: CS207 group 15
Author-email: UNKNOWN
License: UNKNOWN
Platform: UNKNOWN
Requires-Dist: numpy
